Content/Demo_plots.png
Content/Demo_results.png
Content/Demo_terminal.png
Content/Person_selection.png
Content/Video_tuto_Sports2D_Colab.png
Content/huggingface_demo.png
Content/joint_convention.png
Content/paper.bib
Content/paper.md
Content/sports2d_blender.gif
Content/sports2d_opensim.gif
Sports2D/Sports2D.ipynb
Sports2D/Sports2D.py
Sports2D/__init__.py
Sports2D/process.py
Sports2D/Demo/Calib_demo.toml
Sports2D/Demo/Config_demo.toml
Sports2D/Demo/demo.mp4
Sports2D/Utilities/__init__.py
Sports2D/Utilities/common.py
Sports2D/Utilities/tests.py
sports2d-0.8.26.dist-info/licenses/LICENSE
sports2d-0.8.26.dist-info/METADATA
sports2d-0.8.26.dist-info/WHEEL
sports2d-0.8.26.dist-info/entry_points.txt
sports2d-0.8.26.dist-info/top_level.txt
sports2d-0.8.26.dist-info/RECORD
