Metadata-Version: 2.4
Name: sports2d
Version: 0.8.26
Summary: Compute 2D human pose and angles from a video or a webcam.
Author-email: David Pagnon <contact@david-pagnon.com>
Maintainer-email: David Pagnon <contact@david-pagnon.com>
License-Expression: BSD-3-Clause
Project-URL: Homepage, https://github.com/davidpagnon/Sports2D
Project-URL: Bug Tracker, https://github.com/davidpagnon/Sports2D/issues
Keywords: markerless,kinematics,OpenPose,OpenSim,Mocap,biomechanics,sports coaching,pose estimation,joint angles,sports analytics,kinovea
Classifier: Programming Language :: Python :: 3
Classifier: Development Status :: 3 - Alpha
Classifier: Intended Audience :: Science/Research
Classifier: Intended Audience :: Healthcare Industry
Classifier: Intended Audience :: Education
Classifier: Operating System :: OS Independent
Classifier: Topic :: Scientific/Engineering
Classifier: Topic :: Scientific/Engineering :: Image Processing
Classifier: Topic :: Scientific/Engineering :: Medical Science Apps.
Classifier: Topic :: Multimedia :: Graphics
Classifier: Topic :: Multimedia :: Graphics :: 3D Modeling
Requires-Python: >=3.9
License-File: LICENSE
Requires-Dist: imageio_ffmpeg
Requires-Dist: Pose2Sim>=0.10.38
Dynamic: license-file
